apollo_launcher/__init__.py
apollo_launcher/main.py
tec_do_apollo_env_launcher-0.0.2.dist-info/licenses/LICENSE
tec_do_apollo_env_launcher-0.0.2.dist-info/METADATA
tec_do_apollo_env_launcher-0.0.2.dist-info/WHEEL
tec_do_apollo_env_launcher-0.0.2.dist-info/entry_points.txt
tec_do_apollo_env_launcher-0.0.2.dist-info/top_level.txt
tec_do_apollo_env_launcher-0.0.2.dist-info/RECORD
