Metadata-Version: 2.4
Name: tec-do-apollo-env-launcher
Version: 0.0.2
Summary: A zero-dependency Apollo configuration launcher for Python applications
Home-page: https://github.com/yourusername/apollo-launcher
Author: Your Name or Company
Author-email: your.email@example.com
Project-URL: Bug Reports, https://github.com/yourusername/apollo-launcher/issues
Project-URL: Source, https://github.com/yourusername/apollo-launcher
Classifier: Development Status :: 4 - Beta
Classifier: Intended Audience :: Developers
Classifier: Intended Audience :: System Administrators
Classifier: Topic :: Software Development :: Build Tools
Classifier: License :: OSI Approved :: MIT License
Classifier: Programming Language :: Python :: 3
Classifier: Programming Language :: Python :: 3.6
Classifier: Programming Language :: Python :: 3.7
Classifier: Programming Language :: Python :: 3.8
Classifier: Programming Language :: Python :: 3.9
Classifier: Programming Language :: Python :: 3.10
Classifier: Programming Language :: Python :: 3.11
Classifier: Operating System :: OS Independent
Requires-Python: >=3.6
License-File: LICENSE
Dynamic: author
Dynamic: author-email
Dynamic: classifier
Dynamic: description
Dynamic: description-content-type
Dynamic: home-page
Dynamic: license-file
Dynamic: project-url
Dynamic: requires-python
Dynamic: summary
